mptasks/__about__.py
mptasks/__init__.py
mptasks/pool.py
mptasks-0.0.1.dist-info/METADATA
mptasks-0.0.1.dist-info/WHEEL
mptasks-0.0.1.dist-info/licenses/LICENSE.txt
mptasks-0.0.1.dist-info/RECORD
